emoji_writer/__init__.py
emoji_writer/emoji_writer.py
emoji_writer/groups.py
emoji_writer/letters.py
emoji_writer/writer.py
emoji_writer-0.1.0.dist-info/LICENSE.md
emoji_writer-0.1.0.dist-info/METADATA
emoji_writer-0.1.0.dist-info/WHEEL
emoji_writer-0.1.0.dist-info/top_level.txt
emoji_writer-0.1.0.dist-info/RECORD
