Metadata-Version: 2.1
Name: emoji-writer
Version: 0.1.0
Summary: Tool to write words with emojis
Home-page: https://github.com/pllueca/emoji_writer
Author: Pablo Llueca
Author-email: Pablo Llueca <pablo.llueca@gmail.com>
License: MIT License
Project-URL: Homepage, https://github.com/pllueca/emoji_writer
Classifier: Programming Language :: Python :: 3
Classifier: Programming Language :: Python :: 3.6
Classifier: Programming Language :: Python :: 3.7
Classifier: Programming Language :: Python :: 3.8
Classifier: Programming Language :: Python :: 3.9
Classifier: Programming Language :: Python :: 3.10
Classifier: Programming Language :: Python :: 3.11
Classifier: License :: OSI Approved :: MIT License
Classifier: Operating System :: OS Independent
Requires-Python: >=3.6
License-File: LICENSE.md
Requires-Dist: click
Requires-Dist: emoji (==2.2.0)
